pypushoverreceiver/__init__.py
pypushoverreceiver/__main__.py
pypushoverreceiver/client.py
pypushoverreceiver/constants.py
pypushoverreceiver/exceptions.py
pypushoverreceiver/websocket.py
pypushoverreceiver-0.0.3.dist-info/LICENSE
pypushoverreceiver-0.0.3.dist-info/METADATA
pypushoverreceiver-0.0.3.dist-info/WHEEL
pypushoverreceiver-0.0.3.dist-info/top_level.txt
pypushoverreceiver-0.0.3.dist-info/RECORD
